gimap/ArrowRotateMap.png
gimap/ArrowRotateMapAll.png
gimap/GIBigmap_luma_0125x_pad125.png
gimap/GICityInner_05x.png
gimap/GICityOuter_05x.png
gimap/GIMAP_05x.png
gimap/GIMAP_luma_05x.png
gimap/GIReachableMask_0125x_pad125.png
gimap/__init__.py
gimap/__version__.py
gimap-3.4.6.dist-info/LICENSE
gimap-3.4.6.dist-info/METADATA
gimap-3.4.6.dist-info/WHEEL
gimap-3.4.6.dist-info/top_level.txt
gimap-3.4.6.dist-info/RECORD
